autotest/__init__.py
autotest/xml/__init__.py
autotest/xml/xmlCheck.py
smartfeedabcdefg-1.0.0.dist-info/METADATA
smartfeedabcdefg-1.0.0.dist-info/WHEEL
smartfeedabcdefg-1.0.0.dist-info/top_level.txt
smartfeedabcdefg-1.0.0.dist-info/RECORD
