Metadata-Version: 2.1
Name: smartfeedabcdefg
Version: 1.0.0
Summary: 用于smartfeed和流量渠道自动化测试工具包
Home-page: UNKNOWN
Author: zhouyanhui
License: UNKNOWN
Platform: UNKNOWN
